rest_framework_simple_api_key/__init__.py
rest_framework_simple_api_key/admin.py
rest_framework_simple_api_key/apps.py
rest_framework_simple_api_key/backends.py
rest_framework_simple_api_key/crypto.py
rest_framework_simple_api_key/models.py
rest_framework_simple_api_key/mutli_api_crypto.py
rest_framework_simple_api_key/parser.py
rest_framework_simple_api_key/permissions.py
rest_framework_simple_api_key/settings.py
rest_framework_simple_api_key/utils.py
rest_framework_simple_api_key/version.py
rest_framework_simple_api_key/analytics/__init__.py
rest_framework_simple_api_key/analytics/admin.py
rest_framework_simple_api_key/analytics/apps.py
rest_framework_simple_api_key/analytics/middleware.py
rest_framework_simple_api_key/analytics/models.py
rest_framework_simple_api_key/analytics/migrations/0001_initial.py
rest_framework_simple_api_key/analytics/migrations/__init__.py
rest_framework_simple_api_key/management/__init__.py
rest_framework_simple_api_key/management/commands/__init__.py
rest_framework_simple_api_key/management/commands/generate_fernet_key.py
rest_framework_simple_api_key/management/commands/rotation.py
rest_framework_simple_api_key/migrations/0001_initial.py
rest_framework_simple_api_key/migrations/0002_alter_apikey_options.py
rest_framework_simple_api_key/migrations/__init__.py
rest_framework_simple_api_key/rotation/__init__.py
rest_framework_simple_api_key/rotation/admin.py
rest_framework_simple_api_key/rotation/apps.py
rest_framework_simple_api_key/rotation/models.py
rest_framework_simple_api_key/rotation/utils.py
rest_framework_simple_api_key/rotation/migrations/0001_initial.py
rest_framework_simple_api_key/rotation/migrations/__init__.py
djangorestframework_simple_apikey-1.1.1.dist-info/LICENSE
djangorestframework_simple_apikey-1.1.1.dist-info/METADATA
djangorestframework_simple_apikey-1.1.1.dist-info/WHEEL
djangorestframework_simple_apikey-1.1.1.dist-info/top_level.txt
djangorestframework_simple_apikey-1.1.1.dist-info/RECORD
